ucmt/__init__.py
ucmt/cmt.py
ucmt/database.py
ucmt/init.py
ucmt/locate.py
ucmt/main.py
ucmt/path_translator.py
ucmt-0.1.4.dist-info/entry_points.txt
ucmt-0.1.4.dist-info/LICENSE
ucmt-0.1.4.dist-info/WHEEL
ucmt-0.1.4.dist-info/METADATA
ucmt-0.1.4.dist-info/RECORD
