Metadata-Version: 2.1
Name: ucmt
Version: 0.1.4
Summary: ucmt(User Config Management Tool) is the multiplatform(Windows, Mac, Linux) tool managing config in user space.
Home-page: https://github.com/yn-git/User-Config-Management-Tool
License: MIT
Author: Yuya.Nagai
Author-email: ynny.opem@gmail.com
Requires-Python: >=3.6,<4.0
Classifier: License :: OSI Approved :: MIT License
Classifier: Programming Language :: Python :: 3
Classifier: Programming Language :: Python :: 3.6
Classifier: Programming Language :: Python :: 3.7
Classifier: Programming Language :: Python :: 3.8
Provides-Extra: vscode
Requires-Dist: docopt (>=0.6.2,<0.7.0)
Requires-Dist: tinydb (>=3.15.2,<4.0.0)
Project-URL: Repository, https://github.com/yn-git/User-Config-Management-Tool
